uniquery/__init__.py
uniquery/exceptions.py
uniquery/string_utils.py
uniquery/uniquery.py
uniquery/uniquery_postgres.py
uniquery/uniquery_sqlite.py
uniquery/utils.py
uniquery-0.1.0.dist-info/licenses/LICENSE
uniquery-0.1.0.dist-info/METADATA
uniquery-0.1.0.dist-info/WHEEL
uniquery-0.1.0.dist-info/top_level.txt
uniquery-0.1.0.dist-info/RECORD
