Metadata-Version: 2.4
Name: uniquery
Version: 0.1.0
Summary: Raw SQL in. Typed Python objects out. The only ORM that just does ORM.
Author-email: Stefano Menci <stefano.menci@gmail.com>
License: MIT License
Project-URL: Homepage, https://github.com/stenci/UniQuery
Requires-Python: >=3.8
License-File: LICENSE
Requires-Dist: sqlglot
Requires-Dist: python-dotenv
Provides-Extra: postgres
Requires-Dist: psycopg2; extra == "postgres"
Dynamic: license-file
